controller.v
module controller (
    input wire [6:0] opcode,
    input wire [2:0] funct3,
    input wire [6:0] funct7,
    output reg branch, mem_read, mem_to_reg,
    output reg [3:0] alu_op,
    output reg mem_write, alu_src, reg_write, jump
);
    always @(*) begin
        // Default values
        branch = 0; mem_read = 0; mem_to_reg = 0;
        alu_op = 4'b0000;
        mem_write = 0; alu_src = 0; reg_write = 0; jump = 0;

        case (opcode)
            7'b0110011: begin // R-type
                alu_src = 0; reg_write = 1;
                case ({funct7, funct3})
                    {7'b0000000, 3'b000}: alu_op = 4'b0000; // ADD
                    {7'b0100000, 3'b000}: alu_op = 4'b0001; // SUB
                    {7'b0000000, 3'b111}: alu_op = 4'b0010; // AND
                    {7'b0000000, 3'b110}: alu_op = 4'b0011; // OR
                    {7'b0000000, 3'b100}: alu_op = 4'b0100; // XOR
                endcase
            end
            7'b0010011: begin // I-type (addi)
                alu_src = 1; reg_write = 1; alu_op = 4'b0000;
            end
            7'b0000011: begin // LW
                alu_src = 1; mem_to_reg = 1;
                mem_read = 1; reg_write = 1; alu_op = 4'b0000;
            end
            7'b0100011: begin // SW
                alu_src = 1; mem_write = 1; alu_op = 4'b0000;
            end
            7'b1100011: begin // BEQ
                alu_src = 0; branch = 1; alu_op = 4'b0001;
            end
            7'b1101111: begin // JAL
                jump = 1; reg_write = 1;
            end
            7'b1100111: begin // JALR
                jump = 1; reg_write = 1; alu_src = 1;
            end
            7'b0110111: begin // LUI
                reg_write = 1; alu_op = 4'b0111;
            end
            7'b0010111: begin // AUIPC
                reg_write = 1; alu_op = 4'b1000;
            end
        endcase
    end
endmodule

alu.v
module alu (
    input wire [31:0] a, b,
    input wire [3:0] op,
    output reg [31:0] result,
    output wire zero
);
    always @(*) begin
        case (op)
            4'b0000: result = a + b;   // add
            4'b0001: result = a - b;   // sub
            4'b0010: result = a & b;   // and
            4'b0011: result = a | b;   // or
            4'b0100: result = a ^ b;   // xor
            4'b0111: result = b;       // lui
            4'b1000: result = a + b;   // auipc
            default: result = 0;
        endcase
    end
    assign zero = (result == 0);
endmodule

datapath.v
module datapath (
    input wire clk, rst,
    output reg [31:0] pc,
    output wire [31:0] instr,
    output wire [31:0] alu_result,
    input wire [31:0] mem_data,
    output wire [31:0] write_data,
    output wire [31:0] imm,
    output wire [31:0] reg_data1, reg_data2,
    output wire [4:0] rs1, rs2, rd,
    output wire [6:0] opcode,
    output wire [2:0] funct3,
    output wire [6:0] funct7,
    input wire branch, mem_read, mem_to_reg,
    input wire mem_write, alu_src, reg_write, jump,
    input wire [3:0] alu_op,
    output wire zero
);

    reg [31:0] instr_mem [0:255];
    reg [31:0] data_mem [0:255];
    reg [31:0] regfile [0:31];
    wire [31:0] alu_in2;
    wire [31:0] pc_next;

    assign instr = instr_mem[pc[9:2]];

    assign opcode = instr[6:0];
    assign rd     = instr[11:7];
    assign funct3 = instr[14:12];
    assign rs1    = instr[19:15];
    assign rs2    = instr[24:20];
    assign funct7 = instr[31:25];

    assign reg_data1 = regfile[rs1];
    assign reg_data2 = regfile[rs2];

    assign imm = (opcode == 7'b0000011 || opcode == 7'b0010011 || opcode == 7'b1100111) ? 
                    {{20{instr[31]}}, instr[31:20]} :  // I-type
                 (opcode == 7'b0100011) ?
                    {{20{instr[31]}}, instr[31:25], instr[11:7]} : // S-type
                 (opcode == 7'b1100011) ?
                    {{19{instr[31]}}, instr[31], instr[7], instr[30:25], instr[11:8], 1'b0} : // B-type
                 (opcode == 7'b1101111) ?
                    {{11{instr[31]}}, instr[31], instr[19:12], instr[20], instr[30:21], 1'b0} : // JAL
                 (opcode == 7'b0110111 || opcode == 7'b0010111) ?
                    {instr[31:12], 12'b0} : 32'b0;

    assign alu_in2 = alu_src ? imm : reg_data2;

    alu my_alu (
        .a(reg_data1), .b(alu_in2), .op(alu_op),
        .result(alu_result), .zero(zero)
    );

    assign write_data = mem_to_reg ? mem_data : alu_result;

    always @(posedge clk) begin
        if (rst) begin
            pc <= 0;
            regfile[0] <= 0; // x0 is always zero
        end else begin
            if (branch && zero) pc <= pc + imm;
            else if (jump) pc <= reg_data1 + imm; // for jalr
            else pc <= pc + 4;
        end

        if (reg_write && rd != 0)
            regfile[rd] <= write_data;

        if (mem_write)
            data_mem[alu_result[9:2]] <= reg_data2;

        regfile[0] <= 0; // Ensure x0 is always zero
        
    end
endmodule

top.v
module riscv_single_cycle (
    input wire clk,
    input wire rst
);
    wire [31:0] pc, instr, alu_result, mem_data, write_data;
    wire [31:0] imm, reg_data1, reg_data2;
    wire [4:0] rs1, rs2, rd;
    wire [6:0] opcode, funct7;
    wire [2:0] funct3;
    wire branch, mem_read, mem_to_reg, mem_write, alu_src, reg_write, jump;
    wire [3:0] alu_op;
    wire zero;

    datapath dp (
        .clk(clk), .rst(rst),
        .pc(pc), .instr(instr),
        .alu_result(alu_result), .mem_data(mem_data),
        .write_data(write_data), .imm(imm),
        .reg_data1(reg_data1), .reg_data2(reg_data2),
        .rs1(rs1), .rs2(rs2), .rd(rd),
        .opcode(opcode), .funct3(funct3), .funct7(funct7),
        .branch(branch), .mem_read(mem_read),
        .mem_to_reg(mem_to_reg), .mem_write(mem_write),
        .alu_src(alu_src), .reg_write(reg_write),
        .alu_op(alu_op), .zero(zero), .jump(jump)
    );

    controller ctrl (
        .opcode(opcode), .funct3(funct3), .funct7(funct7),
        .branch(branch), .mem_read(mem_read), .mem_to_reg(mem_to_reg),
        .alu_op(alu_op), .mem_write(mem_write),
        .alu_src(alu_src), .reg_write(reg_write), .jump(jump)
    );

endmodule

single_cycle_proccessor_test.v
`timescale 1ns / 1ps

module tb_riscv;

    reg clk;
    reg rst;

    // Instantiate the top-level module
    riscv_single_cycle uut (
        .clk(clk),
        .rst(rst)
    );

    // Clock generation (10 ns period)
    initial begin
        clk = 0;
        forever #5 clk = ~clk;
    end

    // Initial setup and program loading
    initial begin
        $dumpfile("cpu.vcd");
        $dumpvars(0, tb_riscv);

        rst = 1;
        #10 rst = 0;

        // Load program into instruction memory manually
        // Example program: adds two numbers and stores result
        // addi x1, x0, 5
        // addi x2, x0, 10
        // add  x3, x1, x2
        // sw   x3, 0(x0)
        // lw   x4, 0(x0)
        uut.dp.instr_mem[0] = 32'h00500093;  // addi x1, x0, 5
        uut.dp.instr_mem[1] = 32'h00a00113;  // addi x2, x0, 10
        uut.dp.instr_mem[2] = 32'h002081b3;  // add x3, x1, x2
        uut.dp.instr_mem[3] = 32'h00302023;  // sw x3, 0(x0)
        uut.dp.instr_mem[4] = 32'h00002283;  // lw x5, 0(x0)
        uut.dp.instr_mem[5] = 32'h00000013;  // nop (addi x0, x0, 0)

        // Wait some cycles to execute
        #100;

        // Print final register values
        $display("x1 = %d", uut.dp.regfile[1]);
        $display("x2 = %d", uut.dp.regfile[2]);
        $display("x3 = %d", uut.dp.regfile[3]);
        $display("x5 = %d", uut.dp.regfile[5]);  // loaded value

        $finish;
    end
endmodule

cpu.vcd
$date
	Sat Jul 12 21:03:13 2025
$end
$version
	Icarus Verilog
$end
$timescale
	1ps
$end
$scope module tb_riscv $end
$var reg 1 ! clk $end
$var reg 1 " rst $end
$scope module uut $end
$var wire 1 ! clk $end
$var wire 32 # mem_data [31:0] $end
$var wire 1 " rst $end
$var wire 1 $ zero $end
$var wire 32 % write_data [31:0] $end
$var wire 5 & rs2 [4:0] $end
$var wire 5 ' rs1 [4:0] $end
$var wire 1 ( reg_write $end
$var wire 32 ) reg_data2 [31:0] $end
$var wire 32 * reg_data1 [31:0] $end
$var wire 5 + rd [4:0] $end
$var wire 32 , pc [31:0] $end
$var wire 7 - opcode [6:0] $end
$var wire 1 . mem_write $end
$var wire 1 / mem_to_reg $end
$var wire 1 0 mem_read $end
$var wire 1 1 jump $end
$var wire 32 2 instr [31:0] $end
$var wire 32 3 imm [31:0] $end
$var wire 7 4 funct7 [6:0] $end
$var wire 3 5 funct3 [2:0] $end
$var wire 1 6 branch $end
$var wire 1 7 alu_src $end
$var wire 32 8 alu_result [31:0] $end
$var wire 4 9 alu_op [3:0] $end
$scope module ctrl $end
$var wire 7 : opcode [6:0] $end
$var wire 7 ; funct7 [6:0] $end
$var wire 3 < funct3 [2:0] $end
$var reg 4 = alu_op [3:0] $end
$var reg 1 7 alu_src $end
$var reg 1 6 branch $end
$var reg 1 1 jump $end
$var reg 1 0 mem_read $end
$var reg 1 / mem_to_reg $end
$var reg 1 . mem_write $end
$var reg 1 ( reg_write $end
$upscope $end
$scope module dp $end
$var wire 4 > alu_op [3:0] $end
$var wire 1 7 alu_src $end
$var wire 1 6 branch $end
$var wire 1 ! clk $end
$var wire 32 ? instr [31:0] $end
$var wire 1 1 jump $end
$var wire 32 @ mem_data [31:0] $end
$var wire 1 0 mem_read $end
$var wire 1 / mem_to_reg $end
$var wire 1 . mem_write $end
$var wire 32 A reg_data1 [31:0] $end
$var wire 32 B reg_data2 [31:0] $end
$var wire 1 ( reg_write $end
$var wire 1 " rst $end
$var wire 1 $ zero $end
$var wire 32 C write_data [31:0] $end
$var wire 5 D rs2 [4:0] $end
$var wire 5 E rs1 [4:0] $end
$var wire 5 F rd [4:0] $end
$var wire 7 G opcode [6:0] $end
$var wire 32 H imm [31:0] $end
$var wire 7 I funct7 [6:0] $end
$var wire 3 J funct3 [2:0] $end
$var wire 32 K alu_result [31:0] $end
$var wire 32 L alu_in2 [31:0] $end
$var reg 32 M pc [31:0] $end
$scope module my_alu $end
$var wire 32 N a [31:0] $end
$var wire 32 O b [31:0] $end
$var wire 4 P op [3:0] $end
$var wire 1 $ zero $end
$var reg 32 Q result [31:0] $end
$upscope $end
$upscope $end
$upscope $end
$upscope $end
$enddefinitions $end
$comment Show the parameter values. $end
$dumpall
$end
#0
$dumpvars
bx Q
bx P
bx O
bx N
bx M
bx L
bx K
bx J
bx I
bx H
bx G
bx F
bx E
bx D
bx C
bx B
bx A
bz @
bx ?
bx >
bx =
bx <
bx ;
bx :
bx 9
bx 8
x7
x6
bx 5
bx 4
bx 3
bx 2
x1
x0
x/
x.
bx -
bx ,
bx +
bx *
bx )
x(
bx '
bx &
bx %
x$
bz #
1"
0!
$end
#5000
b0 ,
b0 M
1!
#10000
b101 %
b101 C
0$
b101 8
b101 K
b101 Q
b101 L
b101 O
01
1(
17
0.
b0 9
b0 =
b0 >
b0 P
0/
00
06
b101 3
b101 H
b10011 -
b10011 :
b10011 G
b1 +
b1 F
b0 5
b0 <
b0 J
b0 *
b0 A
b0 N
b0 '
b0 E
b101 &
b101 D
b0 4
b0 ;
b0 I
0!
b10100000000000010010011 2
b10100000000000010010011 ?
0"
#15000
b1010 %
b1010 C
b1010 8
b1010 K
b1010 Q
b1010 L
b1010 O
b1010 3
b1010 H
b10 +
b10 F
b1010 &
b1010 D
b101000000000000100010011 2
b101000000000000100010011 ?
b100 ,
b100 M
1!
#20000
0!
#25000
b1111 %
b1111 C
1(
07
b1111 8
b1111 K
b1111 Q
b0 3
b0 H
b110011 -
b110011 :
b110011 G
b11 +
b11 F
b101 *
b101 A
b101 N
b1 '
b1 E
b1010 )
b1010 B
b10 &
b10 D
b1000001000000110110011 2
b1000001000000110110011 ?
b1000 ,
b1000 M
1!
#30000
0!
#35000
b0 %
b0 C
1$
b0 8
b0 K
b0 Q
1.
17
0(
b0 L
b0 O
b100011 -
b100011 :
b100011 G
b0 +
b0 F
b10 5
b10 <
b10 J
b0 *
b0 A
b0 N
b0 '
b0 E
b1111 )
b1111 B
b11 &
b11 D
b1100000010000000100011 2
b1100000010000000100011 ?
b1100 ,
b1100 M
1!
#40000
0!
#45000
bz %
bz C
1(
10
1/
17
0.
b11 -
b11 :
b11 G
b101 +
b101 F
b0 )
b0 B
b0 &
b0 D
b10001010000011 2
b10001010000011 ?
b10000 ,
b10000 M
1!
#50000
0!
#55000
b0 %
b0 C
1(
17
0/
00
b10011 -
b10011 :
b10011 G
b0 +
b0 F
b0 5
b0 <
b0 J
b10011 2
b10011 ?
b10100 ,
b10100 M
1!
#60000
0!
#65000
bx %
bx C
bx L
bx O
x$
bx 8
bx K
bx Q
0(
07
bx 3
bx H
bx -
bx :
bx G
bx +
bx F
bx 5
bx <
bx J
bx *
bx A
bx N
bx '
bx E
bx )
bx B
bx &
bx D
bx 4
bx ;
bx I
bx 2
bx ?
b11000 ,
b11000 M
1!
#70000
0!
#75000
b11100 ,
b11100 M
1!
#80000
0!
#85000
b100000 ,
b100000 M
1!
#90000
0!
#95000
b100100 ,
b100100 M
1!
#100000
0!
#105000
b101000 ,
b101000 M
1!
